imageterminal/__init__.py
imageterminal/__main__.py
imageterminal/main.py
imageterminal/style.tcss
imageterminal-2.0.1.dist-info/entry_points.txt
imageterminal-2.0.1.dist-info/LICENSE.txt
imageterminal-2.0.1.dist-info/METADATA
imageterminal-2.0.1.dist-info/WHEEL
imageterminal-2.0.1.dist-info/RECORD
