Metadata-Version: 2.3
Name: imageterminal
Version: 2.0.1
Summary: A  terminal tool for advanced image manipulation including a filetype converter, background remover, and blazing fast image upscaling!
License: Apache-2.0
Author: Ian Tawileh
Requires-Python: >=3.8
Classifier: License :: OSI Approved :: Apache Software License
Classifier: Programming Language :: Python :: 3
Classifier: Programming Language :: Python :: 3.8
Classifier: Programming Language :: Python :: 3.9
Classifier: Programming Language :: Python :: 3.10
Classifier: Programming Language :: Python :: 3.11
Classifier: Programming Language :: Python :: 3.12
Classifier: Programming Language :: Python :: 3.13
Requires-Dist: numpy (>=2,<3.0.0)
Requires-Dist: onnxruntime (>=1.16.0,<2.0.0)
Requires-Dist: opencv-contrib-python (>=4.12.0.88,<5.0.0.0)
Requires-Dist: pillow (>=11.3.0,<12.0.0)
Requires-Dist: pillow-avif-plugin (>=1.5.2,<2.0.0)
Requires-Dist: rembg (>=2.0.67,<3.0.0)
Requires-Dist: textual (>=5.2.0,<6.0.0)
